sqlalchemy_aip160/__init__.py
sqlalchemy_aip160/aip160_filter.py
sqlalchemy_aip160/py.typed
sqlalchemy_aip160-0.1.3.dist-info/WHEEL
sqlalchemy_aip160-0.1.3.dist-info/METADATA
sqlalchemy_aip160-0.1.3.dist-info/RECORD
