Metadata-Version: 2.3
Name: sqlalchemy-aip160
Version: 0.1.3
Summary: SQLAlchemy support for AIP-160 style filters
Author: Rob Clevenger
Author-email: Rob Clevenger <rob@robsite.org>
Requires-Dist: lark>=1.3.1
Requires-Dist: sqlalchemy>=2.0.44
Requires-Python: >=3.13
Project-URL: Homepage, https://github.com/rcleveng/sqlalchemy_aip160
Project-URL: Issues, https://github.com/rcleveng/sqlalchemy_aip160/issues
